Metadata-Version: 2.1
Name: loducode-maytapi
Version: 0.1.2
Summary: Non official maytapi library python
Home-page: https://github.com/UnTalDulcey/loducode_maytapi
Author: Cristian Dulcey
Author-email: cristian@loducode.com
License: UNKNOWN
Download-URL: https://github.com/UnTalDulcey/loducode_maytapi/tarball/0.1
Keywords: maytapi,whatsapp,loducode
Platform: UNKNOWN
